{"1":{"points":[[26.998415,75.752998],[26.998494,75.752842],[26.998783,75.75174]],"Houses":[{"latlong":{"latitude":"26.9981984","longitude":"75.7536854"},"UID":"E28069950000400EED1421D1","Basicinfo":{"CardNumber":"MPZ153900","MobileNumber":"1111111111"}},{"latlong":{"latitude":"26.9986809","longitude":"75.7530178"},"UID":"E28069950000400EED144D5A","Basicinfo":{"CardNumber":"MPZ166769","MobileNumber":"1111111111"}},{"latlong":{"latitude":"26.9989463","longitude":"75.7518955"},"UID":"E28069950000500EED18795A","Basicinfo":{"CardNumber":"MPZ166774","MobileNumber":"1111111111"}},{"latlong":{"latitude":"26.9975857","longitude":"75.7551165"},"UID":"E28069950000500EED1379BC","Basicinfo":{"CardNumber":"MPZ171604","MobileNumber":"1111111111"}},{"latlong":{"latitude":"26.9973149","longitude":"75.7554036"},"UID":"E28069950000400EED11C57E","Basicinfo":{"CardNumber":"MPZ171606","MobileNumber":"1111111111"}},{"latlong":{"latitude":"26.9983153","longitude":"75.7531338"},"UID":"E28069950000400EED172DBB","Basicinfo":{"CardNumber":"MPZ171620","MobileNumber":"1234567890"}},{"latlong":{"latitude":"26.99764","longitude":"75.754953"},"UID":"E28069950000400EED109D7E","Basicinfo":{"CardNumber":"MPZ171636","MobileNumber":"1111111111"}},{"latlong":{"latitude":"26.9975808","longitude":"75.755022"},"UID":"E28069950000400EED10857E","Basicinfo":{"CardNumber":"MPZ171654","MobileNumber":"1111111111"}},{"latlong":{"latitude":"26.9973919","longitude":"75.7553565"},"UID":"E28069950000400EED160DBB","Basicinfo":{"CardNumber":"MPZ171656","MobileNumber":"1111111111"}},{"latlong":{"latitude":"26.9973569","longitude":"75.7553959"},"UID":"E28069950000400EED166D7E","Basicinfo":{"CardNumber":"MPZ171664","MobileNumber":"1111111111"}},{"latlong":{"latitude":"26.9979799","longitude":"75.7541774"},"UID":"E28069950000400EED10497E","Basicinfo":{"CardNumber":"MPZ171677","MobileNumber":"1111111111"}},{"latlong":{"latitude":"26.9979092","longitude":"75.7542697"},"UID":"E28069950000400EED18F5BB","Basicinfo":{"CardNumber":"MPZ171681","MobileNumber":"1111111111"}},{"latlong":{"latitude":"26.9979209","longitude":"75.7542001"},"UID":"E28069950000500EED13217E","Basicinfo":{"CardNumber":"MPZ171686","MobileNumber":"1111111111"}},{"latlong":{"latitude":"26.9980208","longitude":"75.7541247"},"UID":"E28069950000500EED15F9BB","Basicinfo":{"CardNumber":"MPZ171702","MobileNumber":"1234567890"}},{"latlong":{"latitude":"26.9974319","longitude":"75.7552571"},"UID":"E28069950000500EED14797E","Basicinfo":{"CardNumber":"MPZ171724","MobileNumber":"1111111111"}},{"latlong":{"latitude":"26.9979515","longitude":"75.7542305"},"UID":"E28069950000400EED11C97D","Basicinfo":{"CardNumber":"MPZ171734","MobileNumber":"1111111111"}},{"latlong":{"latitude":"26.9975004","longitude":"75.7552376"},"UID":"E28069950000500EED180D7E","Basicinfo":{"CardNumber":"MPZ171746","MobileNumber":"1111111111"}},{"latlong":{"latitude":"26.9976502","longitude":"75.7548443"},"UID":"E28069950000400EED16317E","Basicinfo":{"CardNumber":"MPZ171757","MobileNumber":"1111111111"}},{"latlong":{"latitude":"26.9975334","longitude":"75.7551"},"UID":"E28069950000400EED14997E","Basicinfo":{"CardNumber":"MPZ171758","MobileNumber":"1111111111"}},{"latlong":{"latitude":"26.9986609","longitude":"75.7528523"},"UID":"E28069950000500EED10CDBC","Basicinfo":{"CardNumber":"MPZ171771","MobileNumber":"1111111111"}},{"latlong":{"latitude":"26.9986686","longitude":"75.752909"},"UID":"E28069950000400EED128DBB","Basicinfo":{"CardNumber":"MPZ171772","MobileNumber":"1111111111"}},{"latlong":{"latitude":"26.998555","longitude":"75.752596"},"UID":"E28069950000500EED11AD7E","Basicinfo":{"CardNumber":"MPZ171791","MobileNumber":"1111111111"}},{"latlong":{"latitude":"26.9983971","longitude":"75.7523893"},"UID":"E28069950000500EED1635BB","Basicinfo":{"CardNumber":"MPZ171793","MobileNumber":"1111111111"}},{"latlong":{"latitude":"26.9981002","longitude":"75.753934"},"UID":"E28069950000500EED17B5BB","Basicinfo":{"CardNumber":"MPZ171799","MobileNumber":"1234567890"}},{"latlong":{"latitude":"26.9973354","longitude":"75.7553445"},"UID":"E28069950000400EED18197C","Basicinfo":{"CardNumber":"MPZ171803","MobileNumber":"1111111111"}},{"latlong":{"latitude":"26.9974844","longitude":"75.755222"},"UID":"E28069950000500EED16817E","Basicinfo":{"CardNumber":"MPZ171804","MobileNumber":"1111111111"}},{"latlong":{"latitude":"26.997495","longitude":"75.7552971"},"UID":"E28069950000400EED1255BB","Basicinfo":{"CardNumber":"MPZ171805","MobileNumber":"1111111111"}},{"latlong":{"latitude":"26.9971617","longitude":"75.7556558"},"UID":"E28069950000400EED177DBB","Basicinfo":{"CardNumber":"MPZ171806","MobileNumber":"1111111111"}},{"latlong":{"latitude":"26.9979886","longitude":"75.7536526"},"UID":"E28069950000500EED13997E","Basicinfo":{"CardNumber":"MPZ171817","MobileNumber":"1234567890"}},{"latlong":{"latitude":"26.9988112","longitude":"75.7524828"},"UID":"E28069950000500EED16B17E","Basicinfo":{"CardNumber":"MPZ171878","MobileNumber":"1111111111"}},{"latlong":{"latitude":"26.9984322","longitude":"75.7528477"},"UID":"E28069950000500EED1681BB","Basicinfo":{"CardNumber":"MPZ171900","MobileNumber":"1234567890"}},{"latlong":{"latitude":"26.9985386","longitude":"75.7526138"},"UID":"E28069950000500EED14D57E","Basicinfo":{"CardNumber":"MPZ171923","MobileNumber":"1111111111"}},{"latlong":{"latitude":"26.9980137","longitude":"75.7540178"},"UID":"E28069950000500EED16A9BB","Basicinfo":{"CardNumber":"MPZ171927","MobileNumber":"1234567890"}},{"latlong":{"latitude":"26.9977086","longitude":"75.7547548"},"UID":"E28069950000400EED1795BB","Basicinfo":{"CardNumber":"MPZ171941","MobileNumber":"1111111111"}},{"latlong":{"latitude":"26.9973963","longitude":"75.7553144"},"UID":"E28069950000400EED13E57E","Basicinfo":{"CardNumber":"MPZ171951","MobileNumber":"1111111111"}},{"latlong":{"latitude":"26.9982924","longitude":"75.7531674"},"UID":"E28069950000500EED18A5BA","Basicinfo":{"CardNumber":"MPZ171967","MobileNumber":"1234567890"}},{"latlong":{"latitude":"26.99874","longitude":"75.7523067"},"UID":"E28069950000500EED19B5BA","Basicinfo":{"CardNumber":"MPZ171970","MobileNumber":"1111111111"}},{"latlong":{"latitude":"26.9985467","longitude":"75.7527404"},"UID":"E28069950000500EED1779BB","Basicinfo":{"CardNumber":"MPZ171987","MobileNumber":"1111111111"}},{"latlong":{"latitude":"26.998591","longitude":"75.7525484"},"UID":"E28069950000400EED11957D","Basicinfo":{"CardNumber":"MPZ172007","MobileNumber":"1111111111"}},{"latlong":{"latitude":"26.9980447","longitude":"75.7535596"},"UID":"E28069950000400EED15497E","Basicinfo":{"CardNumber":"MPZ172008","MobileNumber":"1234567890"}},{"latlong":{"latitude":"26.9988653","longitude":"75.7522708"},"UID":"E28069950000500EED1861BB","Basicinfo":{"CardNumber":"MPZ172019","MobileNumber":"1111111111"}},{"latlong":{"latitude":"26.9980263","longitude":"75.7540019"},"UID":"E28069950000400EED1949BB","Basicinfo":{"CardNumber":"MPZ172037","MobileNumber":"1234567890"}},{"latlong":{"latitude":"26.9980855","longitude":"75.7535035"},"UID":"E28069950000500EED13697D","Basicinfo":{"CardNumber":"MPZ172049","MobileNumber":"1234567890"}},{"latlong":{"latitude":"26.9979682","longitude":"75.7540779"},"UID":"E28069950000400EED12097D","Basicinfo":{"CardNumber":"MPZ172051","MobileNumber":"1234567890"}},{"latlong":{"latitude":"26.9980799","longitude":"75.7534831"},"UID":"E28069950000400EED14957D","Basicinfo":{"CardNumber":"MPZ172052","MobileNumber":"1234567890"}},{"latlong":{"latitude":"26.9986467","longitude":"75.7519067"},"UID":"E28069950000400EED10D57E","Basicinfo":{"CardNumber":"MPZ172079","MobileNumber":"1111111111"}},{"latlong":{"latitude":"26.9978143","longitude":"75.7545352"},"UID":"E28069950000500EED15F98E","Basicinfo":{"CardNumber":"MPZ172381","MobileNumber":"1111111111"}},{"latlong":{"latitude":"26.998421","longitude":"75.7528969"},"UID":"E28069950000400EED12D5BC","Basicinfo":{"CardNumber":"MPZ179734","MobileNumber":"1234567890"}},{"latlong":{"latitude":"26.9981111","longitude":"75.7538381"},"UID":"E280117000000217B0C6E199","Basicinfo":{"CardNumber":"MPZ179745","MobileNumber":"1234567890"}},{"latlong":{"latitude":"26.998426","longitude":"75.7528343"},"UID":"E28069950000500EED1319BC","Basicinfo":{"CardNumber":"MPZ179774","MobileNumber":"1234567890"}},{"latlong":{"latitude":"26.9979519","longitude":"75.7540995"},"UID":"E280117000000217B0C6F018","Basicinfo":{"CardNumber":"MPZ179814","MobileNumber":"1234567890"}},{"latlong":{"latitude":"26.9980896","longitude":"75.7539772"},"UID":"E28069950000400EED133579","Basicinfo":{"CardNumber":"MPZ179929","MobileNumber":"1234567890"}},{"latlong":{"latitude":"26.9980669","longitude":"75.7540805"},"UID":"E28069950000400EED191179","Basicinfo":{"CardNumber":"MPZ179968","MobileNumber":"1234567890"}}],"lineLength":131},"2":{"points":[[26.998783,75.75174],[26.99879,75.751708],[26.998431,75.751608],[26.99836,75.751595],[26.99829,75.751734],[26.99818,75.751796],[26.998061,75.75185],[26.997953,75.751804]],"Houses":[{"latlong":{"latitude":"26.99877","longitude":"75.7517217"},"UID":"E28069950000500EED18017E","Basicinfo":{"CardNumber":"MPZ171963","MobileNumber":"1111111111"}}],"lineLength":108},"3":{"points":[[26.997953,75.751804],[26.997965,75.751795],[26.998062,75.751836],[26.998286,75.751724],[26.998352,75.751577],[26.998345,75.751539],[26.998183,75.751425],[26.998478,75.750457]],"Houses":[],"lineLength":183},"4":{"points":[[26.998478,75.750457],[26.998497,75.750468],[26.998358,75.75094],[26.998322,75.751023],[26.998295,75.751101],[26.998271,75.751178],[26.998264,75.751266],[26.998278,75.751345],[26.998328,75.751432],[26.998382,75.75155],[26.998758,75.751673]],"Houses":[],"lineLength":160},"5":{"points":[[26.998758,75.751673],[26.998805,75.751696],[26.999161,75.750258],[26.99854,75.749979]],"Houses":[{"latlong":{"latitude":"26.999045","longitude":"75.7508667"},"UID":"E28069950000400EED151E57","Basicinfo":{"CardNumber":"MPZ101695","MobileNumber":"1111111111"}},{"latlong":{"latitude":"26.998899","longitude":"75.751325"},"UID":"E28069950000400EED196D5A","Basicinfo":{"CardNumber":"MPZ166821","MobileNumber":"1111111111"}},{"latlong":{"latitude":"26.9990429","longitude":"75.7507063"},"UID":"E28069950000500EED12DDBC","Basicinfo":{"CardNumber":"MPZ179641","MobileNumber":"1111111111"}},{"latlong":{"latitude":"26.9994215","longitude":"75.749464"},"UID":"E28069950000500EED1545BC","Basicinfo":{"CardNumber":"MPZ179679","MobileNumber":"1111111111"}},{"latlong":{"latitude":"26.9990555","longitude":"75.7505733"},"UID":"E28069950000400EED195976","Basicinfo":{"CardNumber":"MPZ179684","MobileNumber":"1111111111"}},{"latlong":{"latitude":"26.9989317","longitude":"75.7510367"},"UID":"E28069950000400EED1359BC","Basicinfo":{"CardNumber":"MPZ179687","MobileNumber":"1111111111"}},{"latlong":{"latitude":"26.998905","longitude":"75.7510767"},"UID":"E28069950000400EED1669BC","Basicinfo":{"CardNumber":"MPZ179702","MobileNumber":"1111111111"}},{"latlong":{"latitude":"26.9992617","longitude":"75.7496483"},"UID":"E28069950000400EED15B1BC","Basicinfo":{"CardNumber":"MPZ179761","MobileNumber":"1111111111"}},{"latlong":{"latitude":"26.9994967","longitude":"75.749655"},"UID":"E28069950000500EED155DBC","Basicinfo":{"CardNumber":"MPZ179833","MobileNumber":"1111111111"}},{"latlong":{"latitude":"26.9988865","longitude":"75.7515599"},"UID":"E28069950000400EED14FD79","Basicinfo":{"CardNumber":"MPZ179931","MobileNumber":"1111111111"}},{"latlong":{"latitude":"26.999171","longitude":"75.7504716"},"UID":"E280117000000217B0C6C8DD","Basicinfo":{"CardNumber":"MPZ179949","MobileNumber":"1111111111"}},{"latlong":{"latitude":"26.9989964","longitude":"75.7510632"},"UID":"E28069950000500EED138579","Basicinfo":{"CardNumber":"MPZ179997","MobileNumber":"1111111111"}}],"lineLength":227},"6":{"points":[[26.99854,75.749979],[26.998197,75.749809],[26.998144,75.749932],[26.998082,75.749943],[26.99801,75.749967],[26.9978,75.750676],[26.998069,75.750777]],"Houses":[],"lineLength":175},"7":{"points":[[26.998069,75.750777],[26.998062,75.750792],[26.9978,75.750693],[26.997681,75.751116],[26.99799,75.751234]],"Houses":[],"lineLength":112},"8":{"points":[[26.99799,75.751234],[26.997985,75.751246],[26.997412,75.751024]],"Houses":[],"lineLength":68},"9":{"points":[[26.997412,75.751024],[26.997357,75.751008],[26.997295,75.75135],[26.997854,75.75157]],"Houses":[],"lineLength":106},"10":{"points":[[26.997854,75.75157],[26.997849,75.751588],[26.997289,75.751369]],"Houses":[],"lineLength":67},"11":{"points":[[26.997289,75.751369],[26.997277,75.751362],[26.997069,75.752409]],"Houses":[],"lineLength":107},"12":{"points":[[26.997069,75.752409],[26.997061,75.752465],[26.996413,75.752148],[26.996389,75.752022],[26.99654,75.750925]],"Houses":[],"lineLength":206},"13":{"points":[[26.99654,75.750925],[26.996554,75.750834],[26.997298,75.751043],[26.997331,75.750858],[26.997376,75.750676],[26.997439,75.750553]],"Houses":[],"lineLength":145},"14":{"points":[[26.997439,75.750553],[26.997447,75.750526],[26.997032,75.750369],[26.996658,75.75027]],"Houses":[],"lineLength":93},"15":{"points":[[26.996658,75.75027],[26.996623,75.75026],[26.996735,75.749834],[26.997499,75.750172]],"Houses":[],"lineLength":139},"16":{"points":[[26.997499,75.750172],[26.997554,75.750201],[26.997475,75.750507],[26.99779,75.750616]],"Houses":[],"lineLength":74},"17":{"points":[[26.99779,75.750616],[26.997993,75.749957],[26.998137,75.749911],[26.99818,75.749804]],"Houses":[],"lineLength":97},"18":{"points":[[26.99818,75.749804],[26.998194,75.749777],[26.996908,75.749168]],"Houses":[],"lineLength":157},"19":{"points":[[26.996908,75.749168],[26.996848,75.74915],[26.996714,75.749719],[26.996575,75.75045],[26.996517,75.750842]],"Houses":[],"lineLength":178},"20":{"points":[[26.996517,75.750842],[26.996487,75.751048],[26.995686,75.750791],[26.995313,75.75067]],"Houses":[],"lineLength":156},"21":{"points":[[26.995313,75.75067],[26.99466,75.750479]],"Houses":[{"latlong":{"latitude":"26.9949951","longitude":"75.7506128"},"UID":"E28069950000500EED1239E5","Basicinfo":{"CardNumber":"MPZ144037","MobileNumber":"1234567890"}},{"latlong":{"latitude":"26.995065","longitude":"75.7505933"},"UID":"E28069950000400EED14061E","Basicinfo":{"CardNumber":"MPZ152556","MobileNumber":"1234567890"}},{"latlong":{"latitude":"26.9948227","longitude":"75.7505915"},"UID":"E28069950000400EED10E5AA","Basicinfo":{"CardNumber":"MPZ152629","MobileNumber":"1234567890"}},{"latlong":{"latitude":"26.9947455","longitude":"75.7505538"},"UID":"E28069950000500EED17DA1E","Basicinfo":{"CardNumber":"MPZ152704","MobileNumber":"1234567890"}},{"latlong":{"latitude":"26.9948675","longitude":"75.7505462"},"UID":"E28069950000500EED11C21D","Basicinfo":{"CardNumber":"MPZ152878","MobileNumber":"1234567890"}},{"latlong":{"latitude":"26.9949897","longitude":"75.7506378"},"UID":"E28069950000400EED15A21B","Basicinfo":{"CardNumber":"MPZ153183","MobileNumber":"1234567890"}},{"latlong":{"latitude":"26.9948606","longitude":"75.7505608"},"UID":"E28069950000500EED193DA2","Basicinfo":{"CardNumber":"MPZ158802","MobileNumber":"1234567890"}},{"latlong":{"latitude":"26.9946767","longitude":"75.7504912"},"UID":"E28069950000500EED16A1FE","Basicinfo":{"CardNumber":"MPZ158903","MobileNumber":"1234567890"}},{"latlong":{"latitude":"26.9947219","longitude":"75.750478"},"UID":"E28069950000500EED12CD5F","Basicinfo":{"CardNumber":"MPZ162097","MobileNumber":"1234567890"}},{"latlong":{"latitude":"26.9947354","longitude":"75.7504873"},"UID":"E28069950000500EED1281B0","Basicinfo":{"CardNumber":"MPZ162217","MobileNumber":"1234567890"}},{"latlong":{"latitude":"26.9950609","longitude":"75.7506081"},"UID":"E28069950000400EED1371FD","Basicinfo":{"CardNumber":"MPZ162342","MobileNumber":"1234567890"}},{"latlong":{"latitude":"26.9950762","longitude":"75.7506183"},"UID":"E28069950000400EED17919E","Basicinfo":{"CardNumber":"MPZ164850","MobileNumber":"1234567890"}}],"lineLength":74},"22":{"points":[[26.99466,75.750479],[26.994644,75.750473],[26.994729,75.750112],[26.995284,75.750261]],"Houses":[{"latlong":{"latitude":"26.9946499","longitude":"75.7502704"},"UID":"E28069950000500EED122240","Basicinfo":{"CardNumber":"MPZ127483","MobileNumber":"1234567890"}},{"latlong":{"latitude":"26.9946368","longitude":"75.749909"},"UID":"E28069950000500EED15C59A","Basicinfo":{"CardNumber":"MPZ127485","MobileNumber":"1234567890"}},{"latlong":{"latitude":"26.9945518","longitude":"75.7500728"},"UID":"E28069950000400EED16E9AF","Basicinfo":{"CardNumber":"MPZ127506","MobileNumber":"1234567890"}},{"latlong":{"latitude":"26.9948629","longitude":"75.7500883"},"UID":"E28069950000400EED16EDAE","Basicinfo":{"CardNumber":"MPZ127509","MobileNumber":"1234567890"}},{"latlong":{"latitude":"26.9945581","longitude":"75.7500573"},"UID":"E28069950000400EED13523F","Basicinfo":{"CardNumber":"MPZ127600","MobileNumber":"1234567890"}},{"latlong":{"latitude":"26.9945566","longitude":"75.7500562"},"UID":"E28069950000400EED17BDAF","Basicinfo":{"CardNumber":"MPZ127622","MobileNumber":"1234567890"}},{"latlong":{"latitude":"26.9946306","longitude":"75.7498751"},"UID":"E28069950000500EED130A3F","Basicinfo":{"CardNumber":"MPZ127628","MobileNumber":"1234567890"}},{"latlong":{"latitude":"26.9946275","longitude":"75.7503818"},"UID":"E28069950000500EED10A99A","Basicinfo":{"CardNumber":"MPZ127653","MobileNumber":"1234567890"}},{"latlong":{"latitude":"26.9946454","longitude":"75.7503666"},"UID":"E28069950000400EED1089C0","Basicinfo":{"CardNumber":"MPZ127689","MobileNumber":"1234567890"}},{"latlong":{"latitude":"26.9946179","longitude":"75.7499737"},"UID":"E28069950000400EED1951AF","Basicinfo":{"CardNumber":"MPZ127831","MobileNumber":"1234567890"}},{"latlong":{"latitude":"26.9951065","longitude":"75.7502241"},"UID":"E28069950000400EED1695E5","Basicinfo":{"CardNumber":"MPZ144135","MobileNumber":"1234567890"}},{"latlong":{"latitude":"26.9949685","longitude":"75.7502072"},"UID":"E28069950000500EED16E9E3","Basicinfo":{"CardNumber":"MPZ144141","MobileNumber":"1234567890"}},{"latlong":{"latitude":"26.9949514","longitude":"75.7501888"},"UID":"E28069950000400EED16F21E","Basicinfo":{"CardNumber":"MPZ152722","MobileNumber":"1234567890"}},{"latlong":{"latitude":"26.9951317","longitude":"75.7502418"},"UID":"E28069950000500EED1229A6","Basicinfo":{"CardNumber":"MPZ152912","MobileNumber":"1234567890"}},{"latlong":{"latitude":"26.9951838","longitude":"75.7503006"},"UID":"E28069950000400EED1289E9","Basicinfo":{"CardNumber":"MPZ158801","MobileNumber":"1234567890"}},{"latlong":{"latitude":"26.9950552","longitude":"75.7502196"},"UID":"E28069950000400EED147601","Basicinfo":{"CardNumber":"MPZ159333","MobileNumber":"1234567890"}},{"latlong":{"latitude":"26.9950311","longitude":"75.7502145"},"UID":"E28069950000400EED11C1B0","Basicinfo":{"CardNumber":"MPZ162276","MobileNumber":"1234567890"}},{"latlong":{"latitude":"26.9949582","longitude":"75.7501687"},"UID":"E28069950000500EED15E95E","Basicinfo":{"CardNumber":"MPZ164680","MobileNumber":"1234567890"}},{"latlong":{"latitude":"26.9945959","longitude":"75.7504325"},"UID":"E28069950000500EED148D5E","Basicinfo":{"CardNumber":"MPZ164715","MobileNumber":"1234567890"}},{"latlong":{"latitude":"26.9945548","longitude":"75.7500661"},"UID":"E280117000000217B0C6E815","Basicinfo":{"CardNumber":"MPZ177643","MobileNumber":"1234567890"}},{"latlong":{"latitude":"26.9949721","longitude":"75.7501832"},"UID":"E280117000000217B0C6F319","Basicinfo":{"CardNumber":"MPZ177655","MobileNumber":"1234567890"}}],"lineLength":102},"23":{"points":[[26.995284,75.750261],[26.996203,75.750512],[26.996535,75.750605]],"Houses":[],"lineLength":142},"24":{"points":[[26.996527,75.7506],[26.996543,75.750606],[26.996605,75.750247],[26.995284,75.749874],[26.99487,75.749705]],"Houses":[{"latlong":{"latitude":"26.9948897","longitude":"75.749795"},"UID":"E28069950000400EED150D9C","Basicinfo":{"CardNumber":"MPZ127430","MobileNumber":"1234567890"}},{"latlong":{"latitude":"26.9952068","longitude":"75.7498177"},"UID":"E28069950000400EED19D1AD","Basicinfo":{"CardNumber":"MPZ127468","MobileNumber":"1234567890"}},{"latlong":{"latitude":"26.9950142","longitude":"75.7497598"},"UID":"E28069950000400EED12B640","Basicinfo":{"CardNumber":"MPZ127470","MobileNumber":"1234567890"}},{"latlong":{"latitude":"26.9950157","longitude":"75.7497923"},"UID":"E28069950000500EED1399AF","Basicinfo":{"CardNumber":"MPZ127484","MobileNumber":"1234567890"}},{"latlong":{"latitude":"26.9948591","longitude":"75.7497793"},"UID":"E28069950000500EED1525AD","Basicinfo":{"CardNumber":"MPZ127623","MobileNumber":"1234567890"}},{"latlong":{"latitude":"26.995126","longitude":"75.7498554"},"UID":"E28069950000400EED14363F","Basicinfo":{"CardNumber":"MPZ127703","MobileNumber":"1234567890"}},{"latlong":{"latitude":"26.9950173","longitude":"75.7497715"},"UID":"E28069950000400EED147640","Basicinfo":{"CardNumber":"MPZ127729","MobileNumber":"1234567890"}},{"latlong":{"latitude":"26.9951235","longitude":"75.7498572"},"UID":"E28069950000400EED15FDAF","Basicinfo":{"CardNumber":"MPZ127739","MobileNumber":"1234567890"}},{"latlong":{"latitude":"26.9948839","longitude":"75.7498038"},"UID":"E28069950000400EED139E3F","Basicinfo":{"CardNumber":"MPZ127788","MobileNumber":"1234567890"}},{"latlong":{"latitude":"26.9951677","longitude":"75.749857"},"UID":"E28069950000500EED13223F","Basicinfo":{"CardNumber":"MPZ128040","MobileNumber":"1234567890"}},{"latlong":{"latitude":"26.9952533","longitude":"75.7498867"},"UID":"E28069950000500EED1159AE","Basicinfo":{"CardNumber":"MPZ128930","MobileNumber":"1111111111"}},{"latlong":{"latitude":"26.9949248","longitude":"75.7497144"},"UID":"E28069950000400EED1375A6","Basicinfo":{"CardNumber":"MPZ151302","MobileNumber":"1111111111"}}],"lineLength":239},"25":{"points":[[26.99487,75.749705],[26.994856,75.749705],[26.994939,75.749379],[26.995543,75.749561],[26.996636,75.749866]],"Houses":[{"latlong":{"latitude":"26.9948675","longitude":"75.7493409"},"UID":"E28069950000500EED186D87","Basicinfo":{"CardNumber":"MPZ101711","MobileNumber":"1111111111"}},{"latlong":{"latitude":"26.9948442","longitude":"75.7497299"},"UID":"E28069950000500EED12BA3F","Basicinfo":{"CardNumber":"MPZ127718","MobileNumber":"1234567890"}},{"latlong":{"latitude":"26.9949468","longitude":"75.7494623"},"UID":"E28069950000500EED1715E4","Basicinfo":{"CardNumber":"MPZ143706","MobileNumber":"1111111111"}},{"latlong":{"latitude":"26.9952371","longitude":"75.7494967"},"UID":"E28069950000400EED1195A5","Basicinfo":{"CardNumber":"MPZ151103","MobileNumber":"1111111111"}},{"latlong":{"latitude":"26.9952067","longitude":"75.7492917"},"UID":"E28069950000400EED1091A5","Basicinfo":{"CardNumber":"MPZ151212","MobileNumber":"1111111111"}},{"latlong":{"latitude":"26.9948233","longitude":"75.7497567"},"UID":"E28069950000400EED103DAA","Basicinfo":{"CardNumber":"MPZ151347","MobileNumber":"1111111111"}},{"latlong":{"latitude":"26.9948773","longitude":"75.7496307"},"UID":"E28069950000400EED13E5AA","Basicinfo":{"CardNumber":"MPZ151380","MobileNumber":"1111111111"}},{"latlong":{"latitude":"26.994795","longitude":"75.749705"},"UID":"E28069950000400EED17C5D1","Basicinfo":{"CardNumber":"MPZ153674","MobileNumber":"1111111111"}},{"latlong":{"latitude":"26.9948048","longitude":"75.7496835"},"UID":"E28069950000400EED17ADD0","Basicinfo":{"CardNumber":"MPZ153810","MobileNumber":"1111111111"}},{"latlong":{"latitude":"26.9951852","longitude":"75.7493954"},"UID":"E28069950000400EED19D9A5","Basicinfo":{"CardNumber":"MPZ153896","MobileNumber":"1111111111"}},{"latlong":{"latitude":"26.9951846","longitude":"75.7493127"},"UID":"E28069950000500EED1939CF","Basicinfo":{"CardNumber":"MPZ153901","MobileNumber":"1111111111"}},{"latlong":{"latitude":"26.9951777","longitude":"75.7494174"},"UID":"E28069950000500EED1429D1","Basicinfo":{"CardNumber":"MPZ153942","MobileNumber":"1111111111"}},{"latlong":{"latitude":"26.9947044","longitude":"75.7497087"},"UID":"E28069950000400EED1229A2","Basicinfo":{"CardNumber":"MPZ159481","MobileNumber":"1111111111"}},{"latlong":{"latitude":"26.9948228","longitude":"75.7493452"},"UID":"E28069950000500EED141DA1","Basicinfo":{"CardNumber":"MPZ159600","MobileNumber":"1111111111"}},{"latlong":{"latitude":"26.9947148","longitude":"75.7496558"},"UID":"E28069950000500EED10699F","Basicinfo":{"CardNumber":"MPZ163081","MobileNumber":"1111111111"}},{"latlong":{"latitude":"26.994785","longitude":"75.74972"},"UID":"E28069950000500EED138227","Basicinfo":{"CardNumber":"MPZ172257","MobileNumber":"1111111111"}},{"latlong":{"latitude":"26.9947654","longitude":"75.7497283"},"UID":"E28069950000500EED197135","Basicinfo":{"CardNumber":"MPZ172398","MobileNumber":"1111111111"}}],"lineLength":229},"26":{"points":[[26.996636,75.749866],[26.99667,75.749867],[26.99673,75.749532],[26.995138,75.749065],[26.995064,75.749376]],"Houses":[],"lineLength":252},"27":{"points":[[26.995064,75.749376],[26.995049,75.749371],[26.995123,75.749059],[26.994669,75.748925],[26.994147,75.748779]],"Houses":[{"latlong":{"latitude":"26.994935","longitude":"75.7490117"},"UID":"E28069950000500EED15A5E4","Basicinfo":{"CardNumber":"MPZ143696","MobileNumber":"1111111111"}},{"latlong":{"latitude":"26.9950172","longitude":"75.7489917"},"UID":"E28069950000500EED1689E5","Basicinfo":{"CardNumber":"MPZ143700","MobileNumber":"1111111111"}},{"latlong":{"latitude":"26.9950128","longitude":"75.7490181"},"UID":"E28069950000500EED1071E4","Basicinfo":{"CardNumber":"MPZ143847","MobileNumber":"1111111111"}},{"latlong":{"latitude":"26.9950846","longitude":"75.7491662"},"UID":"E28069950000500EED19C95A","Basicinfo":{"CardNumber":"MPZ166669","MobileNumber":"1111111111"}},{"latlong":{"latitude":"26.995095","longitude":"75.7491267"},"UID":"E28069950000500EED174D5B","Basicinfo":{"CardNumber":"MPZ166681","MobileNumber":"1111111111"}},{"latlong":{"latitude":"26.995075","longitude":"75.7490067"},"UID":"E28069950000500EED10F55A","Basicinfo":{"CardNumber":"MPZ166698","MobileNumber":"1111111111"}},{"latlong":{"latitude":"26.9948234","longitude":"75.7488679"},"UID":"E28069950000500EED16BD59","Basicinfo":{"CardNumber":"MPZ166712","MobileNumber":"1111111111"}},{"latlong":{"latitude":"26.9949133","longitude":"75.7489733"},"UID":"E28069950000400EED184D59","Basicinfo":{"CardNumber":"MPZ166739","MobileNumber":"1111111111"}},{"latlong":{"latitude":"26.99468","longitude":"75.7489148"},"UID":"E28069950000500EED199959","Basicinfo":{"CardNumber":"MPZ166787","MobileNumber":"1111111111"}},{"latlong":{"latitude":"26.9950271","longitude":"75.7493725"},"UID":"E28069950000400EED168959","Basicinfo":{"CardNumber":"MPZ166829","MobileNumber":"1111111111"}},{"latlong":{"latitude":"26.9950958","longitude":"75.749118"},"UID":"E28069950000500EED18BD58","Basicinfo":{"CardNumber":"MPZ166854","MobileNumber":"1111111111"}},{"latlong":{"latitude":"26.9950985","longitude":"75.7490074"},"UID":"E28069950000500EED172D58","Basicinfo":{"CardNumber":"MPZ166870","MobileNumber":"1111111111"}},{"latlong":{"latitude":"26.9950849","longitude":"75.7491599"},"UID":"E28069950000500EED193959","Basicinfo":{"CardNumber":"MPZ167043","MobileNumber":"1111111111"}},{"latlong":{"latitude":"26.9951067","longitude":"75.749035"},"UID":"E28069950000400EED14C55A","Basicinfo":{"CardNumber":"MPZ167396","MobileNumber":"1111111111"}},{"latlong":{"latitude":"26.9944368","longitude":"75.7488801"},"UID":"E28069950000400EED1525BB","Basicinfo":{"CardNumber":"MPZ171660","MobileNumber":"1111111111"}}],"lineLength":145},"28":{"points":[[26.994147,75.748779],[26.994078,75.748767],[26.994016,75.748788],[26.993966,75.748874],[26.993808,75.749362],[26.993752,75.749562]],"Houses":[{"latlong":{"latitude":"26.9938023","longitude":"75.7494692"},"UID":"E28069950000500EED14DDE3","Basicinfo":{"CardNumber":"MPZ143445","MobileNumber":"1111111111"}},{"latlong":{"latitude":"26.9936718","longitude":"75.7493887"},"UID":"E28069950000400EED164DE3","Basicinfo":{"CardNumber":"MPZ143717","MobileNumber":"1111111111"}},{"latlong":{"latitude":"26.9939313","longitude":"75.7490881"},"UID":"E28069950000500EED143D59","Basicinfo":{"CardNumber":"MPZ166820","MobileNumber":"1111111111"}},{"latlong":{"latitude":"26.9937613","longitude":"75.7494093"},"UID":"E28069950000500EED173159","Basicinfo":{"CardNumber":"MPZ166835","MobileNumber":"1111111111"}},{"latlong":{"latitude":"26.9940899","longitude":"75.7487713"},"UID":"E28069950000400EED172958","Basicinfo":{"CardNumber":"MPZ166884","MobileNumber":"1111111111"}},{"latlong":{"latitude":"26.9937052","longitude":"75.7493899"},"UID":"E28069950000400EED190558","Basicinfo":{"CardNumber":"MPZ166931","MobileNumber":"1111111111"}},{"latlong":{"latitude":"26.9937751","longitude":"75.7494459"},"UID":"E28069950000400EED15E158","Basicinfo":{"CardNumber":"MPZ167002","MobileNumber":"1111111111"}},{"latlong":{"latitude":"26.993605","longitude":"75.7493233"},"UID":"E28069950000500EED11E959","Basicinfo":{"CardNumber":"MPZ167024","MobileNumber":"1111111111"}},{"latlong":{"latitude":"26.9936552","longitude":"75.7493992"},"UID":"E28069950000400EED13155A","Basicinfo":{"CardNumber":"MPZ167364","MobileNumber":"1111111111"}},{"latlong":{"latitude":"26.9937009","longitude":"75.7493804"},"UID":"E28069950000400EED11095A","Basicinfo":{"CardNumber":"MPZ167367","MobileNumber":"1111111111"}},{"latlong":{"latitude":"26.9939108","longitude":"75.7490597"},"UID":"E28069950000400EED125559","Basicinfo":{"CardNumber":"MPZ167388","MobileNumber":"1111111111"}},{"latlong":{"latitude":"26.993717","longitude":"75.7493394"},"UID":"E28069950000400EED1271BB","Basicinfo":{"CardNumber":"MPZ171718","MobileNumber":"1111111111"}},{"latlong":{"latitude":"26.9938597","longitude":"75.749253"},"UID":"E28069950000500EED1449BB","Basicinfo":{"CardNumber":"MPZ171973","MobileNumber":"1111112111"}}],"lineLength":97},"29":{"points":[[26.993752,75.749562],[26.993745,75.749581],[26.994367,75.749634]],"Houses":[],"lineLength":71},"30":{"points":[[26.994367,75.749634],[26.994357,75.749649],[26.994269,75.749641],[26.994272,75.749992]],"Houses":[{"latlong":{"latitude":"26.99442","longitude":"75.7496833"},"UID":"E28069950000400EED15F9E3","Basicinfo":{"CardNumber":"MPZ143651","MobileNumber":"1111111111"}},{"latlong":{"latitude":"26.9944484","longitude":"75.7496328"},"UID":"E28069950000500EED10F201","Basicinfo":{"CardNumber":"MPZ163163","MobileNumber":"1111111111"}},{"latlong":{"latitude":"26.994295","longitude":"75.7498833"},"UID":"E28069950000400EED17F158","Basicinfo":{"CardNumber":"MPZ166911","MobileNumber":"1111111111"}},{"latlong":{"latitude":"26.9942761","longitude":"75.7496462"},"UID":"E28069950000400EED10495A","Basicinfo":{"CardNumber":"MPZ167284","MobileNumber":"1111111111"}},{"latlong":{"latitude":"26.9942949","longitude":"75.749911"},"UID":"E28069950000500EED18E15B","Basicinfo":{"CardNumber":"MPZ167355","MobileNumber":"1111111111"}}],"lineLength":46},"31":{"points":[[26.994272,75.749992],[26.994264,75.749988],[26.994262,75.749649],[26.993732,75.749595],[26.99364,75.749955]],"Houses":[{"latlong":{"latitude":"26.9937046","longitude":"75.7496282"},"UID":"E28069950000400EED1901E4","Basicinfo":{"CardNumber":"MPZ143554","MobileNumber":"1111111111"}},{"latlong":{"latitude":"26.9939738","longitude":"75.7496528"},"UID":"E28069950000500EED1249E4","Basicinfo":{"CardNumber":"MPZ143750","MobileNumber":"1111111111"}},{"latlong":{"latitude":"26.9936899","longitude":"75.7498983"},"UID":"E28069950000500EED1735A1","Basicinfo":{"CardNumber":"MPZ159440","MobileNumber":"1111111111"}},{"latlong":{"latitude":"26.993641","longitude":"75.7496268"},"UID":"E28069950000400EED11E5FD","Basicinfo":{"CardNumber":"MPZ163269","MobileNumber":"1111111111"}},{"latlong":{"latitude":"26.9936667","longitude":"75.7496267"},"UID":"E28069950000400EED11899D","Basicinfo":{"CardNumber":"MPZ163411","MobileNumber":"1111111111"}},{"latlong":{"latitude":"26.9939117","longitude":"75.7498217"},"UID":"E28069950000400EED13B19D","Basicinfo":{"CardNumber":"MPZ163534","MobileNumber":"1111111111"}},{"latlong":{"latitude":"26.9935464","longitude":"75.7496017"},"UID":"E28069950000500EED15AD9D","Basicinfo":{"CardNumber":"MPZ163552","MobileNumber":"1111111111"}},{"latlong":{"latitude":"26.9936798","longitude":"75.7496812"},"UID":"E28069950000400EED14CD9D","Basicinfo":{"CardNumber":"MPZ163558","MobileNumber":"1111111111"}},{"latlong":{"latitude":"26.9936004","longitude":"75.7496581"},"UID":"E28069950000400EED163558","Basicinfo":{"CardNumber":"MPZ166940","MobileNumber":"1111111111"}},{"latlong":{"latitude":"26.9939651","longitude":"75.7496374"},"UID":"E28069950000400EED107559","Basicinfo":{"CardNumber":"MPZ167385","MobileNumber":"1111111111"}},{"latlong":{"latitude":"26.9939388","longitude":"75.7498007"},"UID":"E28069950000500EED18A1BB","Basicinfo":{"CardNumber":"MPZ171778","MobileNumber":"1111111111"}},{"latlong":{"latitude":"26.9936767","longitude":"75.7498767"},"UID":"E28069950000400EED14A97E","Basicinfo":{"CardNumber":"MPZ171891","MobileNumber":"1111111112"}}],"lineLength":130},"32":{"points":[[26.99364,75.749955],[26.993628,75.750002],[26.993983,75.750086]],"Houses":[{"latlong":{"latitude":"26.9937041","longitude":"75.7500252"},"UID":"E28069950000400EED1195E4","Basicinfo":{"CardNumber":"MPZ143596","MobileNumber":"1234567890"}},{"latlong":{"latitude":"26.9935903","longitude":"75.7499925"},"UID":"E28069950000400EED116DA1","Basicinfo":{"CardNumber":"MPZ159459","MobileNumber":"1234567890"}},{"latlong":{"latitude":"26.9937063","longitude":"75.7500235"},"UID":"E28069950000400EED175959","Basicinfo":{"CardNumber":"MPZ166823","MobileNumber":"1234567890"}},{"latlong":{"latitude":"26.9938574","longitude":"75.7500396"},"UID":"E28069950000400EED174558","Basicinfo":{"CardNumber":"MPZ166838","MobileNumber":"1234567890"}},{"latlong":{"latitude":"26.9938187","longitude":"75.7500444"},"UID":"E28069950000400EED16495A","Basicinfo":{"CardNumber":"MPZ167291","MobileNumber":"1234567890"}}],"lineLength":45},"33":{"points":[[26.993983,75.750086],[26.993971,75.750102],[26.993625,75.750019],[26.993564,75.750344],[26.994067,75.750455]],"Houses":[{"latlong":{"latitude":"26.9941049","longitude":"75.7503832"},"UID":"E28069950000400EED186254","Basicinfo":{"CardNumber":"MPZ103092","MobileNumber":"1234567890"}},{"latlong":{"latitude":"26.9938611","longitude":"75.7500986"},"UID":"E28069950000400EED16C5E9","Basicinfo":{"CardNumber":"MPZ143451","MobileNumber":"1234567890"}},{"latlong":{"latitude":"26.9940186","longitude":"75.7501099"},"UID":"E28069950000400EED1911E5","Basicinfo":{"CardNumber":"MPZ143587","MobileNumber":"1234567890"}},{"latlong":{"latitude":"26.9934866","longitude":"75.7499845"},"UID":"E28069950000400EED17B9A1","Basicinfo":{"CardNumber":"MPZ159447","MobileNumber":"1234567890"}},{"latlong":{"latitude":"26.9939048","longitude":"75.7501048"},"UID":"E28069950000500EED130DA1","Basicinfo":{"CardNumber":"MPZ159503","MobileNumber":"1234567890"}},{"latlong":{"latitude":"26.9940807","longitude":"75.7504353"},"UID":"E28069950000500EED1089A2","Basicinfo":{"CardNumber":"MPZ159552","MobileNumber":"1234567890"}},{"latlong":{"latitude":"26.9940717","longitude":"75.7504517"},"UID":"E28069950000500EED10B5FD","Basicinfo":{"CardNumber":"MPZ163205","MobileNumber":"1234567890"}},{"latlong":{"latitude":"26.9937942","longitude":"75.7500581"},"UID":"E28069950000400EED15C99D","Basicinfo":{"CardNumber":"MPZ163490","MobileNumber":"1234567890"}},{"latlong":{"latitude":"26.993675","longitude":"75.7503638"},"UID":"E28069950000400EED119D9D","Basicinfo":{"CardNumber":"MPZ163535","MobileNumber":"1234567890"}},{"latlong":{"latitude":"26.9940478","longitude":"75.7501439"},"UID":"E28069950000400EED14D99D","Basicinfo":{"CardNumber":"MPZ163551","MobileNumber":"1234567890"}},{"latlong":{"latitude":"26.9940262","longitude":"75.7501404"},"UID":"E28069950000500EED192159","Basicinfo":{"CardNumber":"MPZ166780","MobileNumber":"1234567890"}},{"latlong":{"latitude":"26.9939333","longitude":"75.750085"},"UID":"E28069950000500EED192958","Basicinfo":{"CardNumber":"MPZ166895","MobileNumber":"1234567890"}},{"latlong":{"latitude":"26.993895","longitude":"75.7504014"},"UID":"E28069950000400EED19B959","Basicinfo":{"CardNumber":"MPZ166948","MobileNumber":"1234567890"}},{"latlong":{"latitude":"26.9939532","longitude":"75.7504105"},"UID":"E28069950000400EED15015A","Basicinfo":{"CardNumber":"MPZ166984","MobileNumber":"1234567890"}},{"latlong":{"latitude":"26.9936123","longitude":"75.7503076"},"UID":"E28069950000400EED10615A","Basicinfo":{"CardNumber":"MPZ167218","MobileNumber":"1234567890"}}],"lineLength":131},"34":{"points":[[26.994067,75.750455],[26.994053,75.750458],[26.993561,75.750359],[26.993503,75.750672]],"Houses":[{"latlong":{"latitude":"26.9940852","longitude":"75.7505372"},"UID":"E28069950000500EED12A602","Basicinfo":{"CardNumber":"MPZ159170","MobileNumber":"1234567890"}},{"latlong":{"latitude":"26.9937964","longitude":"75.7504051"},"UID":"E28069950000500EED14659D","Basicinfo":{"CardNumber":"MPZ163528","MobileNumber":"1234567890"}},{"latlong":{"latitude":"26.9939819","longitude":"75.7504628"},"UID":"E28069950000500EED18659D","Basicinfo":{"CardNumber":"MPZ163579","MobileNumber":"1234567890"}}],"lineLength":88},"35":{"points":[[26.993503,75.750672],[26.9935,75.750695],[26.993984,75.750821]],"Houses":[],"lineLength":57},"36":{"points":[[26.993984,75.750821],[26.99397,75.750829],[26.993502,75.75071],[26.993404,75.751059],[26.99411,75.751212]],"Houses":[{"latlong":{"latitude":"26.9939022","longitude":"75.7508722"},"UID":"E28069950000400EED16ADE4","Basicinfo":{"CardNumber":"MPZ143460","MobileNumber":"1111111111"}},{"latlong":{"latitude":"26.9939937","longitude":"75.7508954"},"UID":"E28069950000500EED1271E3","Basicinfo":{"CardNumber":"MPZ143663","MobileNumber":"1111111111"}},{"latlong":{"latitude":"26.9937831","longitude":"75.7508069"},"UID":"E28069950000500EED193559","Basicinfo":{"CardNumber":"MPZ166784","MobileNumber":"1111111111"}},{"latlong":{"latitude":"26.9937121","longitude":"75.7508003"},"UID":"E28069950000500EED16F559","Basicinfo":{"CardNumber":"MPZ166833","MobileNumber":"1111111111"}},{"latlong":{"latitude":"26.993757","longitude":"75.7508212"},"UID":"E28069950000400EED191158","Basicinfo":{"CardNumber":"MPZ166855","MobileNumber":"1111111111"}},{"latlong":{"latitude":"26.9936859","longitude":"75.7508021"},"UID":"E28069950000500EED119159","Basicinfo":{"CardNumber":"MPZ167100","MobileNumber":"1111111111"}},{"latlong":{"latitude":"26.9936963","longitude":"75.7507803"},"UID":"E28069950000400EED14ED59","Basicinfo":{"CardNumber":"MPZ167135","MobileNumber":"1111111111"}},{"latlong":{"latitude":"26.9937131","longitude":"75.7511589"},"UID":"E28069950000400EED19B5BB","Basicinfo":{"CardNumber":"MPZ171616","MobileNumber":"6375515313"}},{"latlong":{"latitude":"26.9934121","longitude":"75.7508234"},"UID":"E28069950000400EED13AD7E","Basicinfo":{"CardNumber":"MPZ171641","MobileNumber":"1111111111"}},{"latlong":{"latitude":"26.9937595","longitude":"75.7511456"},"UID":"E28069950000500EED14857E","Basicinfo":{"CardNumber":"MPZ171700","MobileNumber":"1111111111"}},{"latlong":{"latitude":"26.9938405","longitude":"75.7511892"},"UID":"E28069950000400EED12357E","Basicinfo":{"CardNumber":"MPZ171725","MobileNumber":"9784878503"}},{"latlong":{"latitude":"26.9940309","longitude":"75.7512139"},"UID":"E28069950000500EED15217E","Basicinfo":{"CardNumber":"MPZ171735","MobileNumber":"7908421380"}},{"latlong":{"latitude":"26.9940869","longitude":"75.7512553"},"UID":"E28069950000500EED120D7E","Basicinfo":{"CardNumber":"MPZ171736","MobileNumber":"9314432532"}},{"latlong":{"latitude":"26.9934741","longitude":"75.7507815"},"UID":"E28069950000400EED191DBA","Basicinfo":{"CardNumber":"MPZ171742","MobileNumber":"1111111111"}},{"latlong":{"latitude":"26.9933518","longitude":"75.7509424"},"UID":"E28069950000400EED18BDBB","Basicinfo":{"CardNumber":"MPZ171744","MobileNumber":"1111111111"}},{"latlong":{"latitude":"26.99375","longitude":"75.7511567"},"UID":"E28069950000500EED12ADBB","Basicinfo":{"CardNumber":"MPZ171801","MobileNumber":"8209448855"}},{"latlong":{"latitude":"26.9938232","longitude":"75.7511455"},"UID":"E28069950000500EED18B9BB","Basicinfo":{"CardNumber":"MPZ171848","MobileNumber":"1111111111"}},{"latlong":{"latitude":"26.9934287","longitude":"75.7507897"},"UID":"E28069950000500EED16DD7E","Basicinfo":{"CardNumber":"MPZ171944","MobileNumber":"1111111111"}},{"latlong":{"latitude":"26.9939583","longitude":"75.7511884"},"UID":"E28069950000500EED1669BB","Basicinfo":{"CardNumber":"MPZ171948","MobileNumber":"1111111111"}},{"latlong":{"latitude":"26.9940878","longitude":"75.7512477"},"UID":"E28069950000400EED1495BB","Basicinfo":{"CardNumber":"MPZ171997","MobileNumber":"9314432532"}}],"lineLength":170},"37":{"points":[[26.99411,75.751212],[26.994127,75.751213],[26.994364,75.75013]],"Houses":[{"latlong":{"latitude":"26.9942221","longitude":"75.7507019"},"UID":"E28069950000400EED1111E4","Basicinfo":{"CardNumber":"MPZ143788","MobileNumber":"1111111111"}},{"latlong":{"latitude":"26.9943451","longitude":"75.7501709"},"UID":"E28069950000400EED14BD5A","Basicinfo":{"CardNumber":"MPZ166637","MobileNumber":"1111111111"}},{"latlong":{"latitude":"26.9941593","longitude":"75.7510396"},"UID":"E28069950000400EED1209BB","Basicinfo":{"CardNumber":"MPZ171717","MobileNumber":"1111111111"}},{"latlong":{"latitude":"26.9941686","longitude":"75.751019"},"UID":"E28069950000400EED11217D","Basicinfo":{"CardNumber":"MPZ172085","MobileNumber":"1111111111"}}],"lineLength":112},"38":{"points":[[26.994364,75.75013],[26.994378,75.750136],[26.99416,75.751228]],"Houses":[{"latlong":{"latitude":"26.994308","longitude":"75.750506"},"UID":"E28069950000400EED168DE5","Basicinfo":{"CardNumber":"MPZ143483","MobileNumber":"1111111111"}},{"latlong":{"latitude":"26.9943556","longitude":"75.7500639"},"UID":"E28069950000400EED14C5E7","Basicinfo":{"CardNumber":"MPZ143669","MobileNumber":"1111111111"}},{"latlong":{"latitude":"26.9943796","longitude":"75.7501052"},"UID":"E28069950000500EED149DE4","Basicinfo":{"CardNumber":"MPZ143688","MobileNumber":"1111111111"}},{"latlong":{"latitude":"26.9943063","longitude":"75.75061"},"UID":"E28069950000400EED16C5E5","Basicinfo":{"CardNumber":"MPZ143718","MobileNumber":"1111111111"}},{"latlong":{"latitude":"26.9942049","longitude":"75.7510597"},"UID":"E28069950000500EED19795B","Basicinfo":{"CardNumber":"MPZ166665","MobileNumber":"1111111111"}}],"lineLength":112},"39":{"points":[[26.99416,75.751228],[26.994156,75.75127],[26.994411,75.751339],[26.994632,75.750522]],"Houses":[{"latlong":{"latitude":"26.9944818","longitude":"75.7512782"},"UID":"E28069950000400EED12417E","Basicinfo":{"CardNumber":"MPZ171777","MobileNumber":"1111111111"}},{"latlong":{"latitude":"26.9945146","longitude":"75.7512273"},"UID":"E28069950000400EED1855BB","Basicinfo":{"CardNumber":"MPZ171800","MobileNumber":"1111111111"}},{"latlong":{"latitude":"26.9942617","longitude":"75.7513009"},"UID":"E28069950000500EED16057E","Basicinfo":{"CardNumber":"MPZ171888","MobileNumber":"1111111111"}},{"latlong":{"latitude":"26.9942693","longitude":"75.7513118"},"UID":"E28069950000500EED197DBB","Basicinfo":{"CardNumber":"MPZ171932","MobileNumber":"1111111111"}}],"lineLength":117},"40":{"points":[[26.994632,75.750522],[26.994643,75.750524],[26.994514,75.751008],[26.994817,75.751115],[26.994874,75.750958]],"Houses":[{"latlong":{"latitude":"26.9946181","longitude":"75.7509105"},"UID":"E28069950000400EED1845E3","Basicinfo":{"CardNumber":"MPZ143603","MobileNumber":"1111111111"}}],"lineLength":103},"41":{"points":[[26.994874,75.750958],[26.994887,75.750965],[26.99483,75.751134],[26.995132,75.751234],[26.995224,75.75098]],"Houses":[],"lineLength":81},"42":{"points":[[26.995224,75.75098],[26.99524,75.75098],[26.995146,75.751228],[26.995508,75.751362],[26.995578,75.751113]],"Houses":[],"lineLength":96},"43":{"points":[[26.995578,75.751113],[26.995588,75.751118],[26.995512,75.751377],[26.995401,75.751339],[26.995298,75.751725]],"Houses":[],"lineLength":81},"44":{"points":[[26.995298,75.751725],[26.99577,75.751885],[26.99592,75.751343],[26.995915,75.751297],[26.995752,75.75125]],"Houses":[],"lineLength":134},"45":{"points":[[26.995752,75.75125],[26.995756,75.75124],[26.995993,75.751312],[26.996431,75.751456]],"Houses":[],"lineLength":78},"46":{"points":[[26.996431,75.751456],[26.996372,75.751884],[26.996348,75.75209],[26.995834,75.751913]],"Houses":[],"lineLength":123},"47":{"points":[[26.995834,75.751913],[26.995806,75.751913],[26.995275,75.751739],[26.994874,75.751586],[26.994654,75.751465],[26.99441,75.751385]],"Houses":[],"lineLength":166},"48":{"points":[[26.99441,75.751385],[26.994103,75.751291],[26.993341,75.751117],[26.992901,75.750993],[26.993119,75.749759]],"Houses":[{"latlong":{"latitude":"26.9935165","longitude":"75.7511389"},"UID":"E28069950000500EED129DBB","Basicinfo":{"CardNumber":"MPZ171639","MobileNumber":"1111111111"}},{"latlong":{"latitude":"26.9936608","longitude":"75.7512026"},"UID":"E28069950000400EED1455BB","Basicinfo":{"CardNumber":"MPZ171678","MobileNumber":"1111111111"}},{"latlong":{"latitude":"26.9939766","longitude":"75.7513028"},"UID":"E28069950000400EED1619BB","Basicinfo":{"CardNumber":"MPZ171682","MobileNumber":"9660237790"}},{"latlong":{"latitude":"26.993511","longitude":"75.7511759"},"UID":"E28069950000500EED14D97E","Basicinfo":{"CardNumber":"MPZ171712","MobileNumber":"1111111111"}},{"latlong":{"latitude":"26.9937867","longitude":"75.7512514"},"UID":"E28069950000500EED160935","Basicinfo":{"CardNumber":"MPZ171726","MobileNumber":"9950700254"}},{"latlong":{"latitude":"26.9940989","longitude":"75.7513041"},"UID":"E28069950000400EED15257E","Basicinfo":{"CardNumber":"MPZ171727","MobileNumber":"9829044545"}},{"latlong":{"latitude":"26.9939548","longitude":"75.7513133"},"UID":"E28069950000400EED1895BB","Basicinfo":{"CardNumber":"MPZ171741","MobileNumber":"9660237790"}},{"latlong":{"latitude":"26.9935801","longitude":"75.7511668"},"UID":"E28069950000400EED12BD7E","Basicinfo":{"CardNumber":"MPZ171743","MobileNumber":"1111111111"}},{"latlong":{"latitude":"26.9939511","longitude":"75.7512386"},"UID":"E28069950000500EED1835BA","Basicinfo":{"CardNumber":"MPZ171773","MobileNumber":"1111111111"}},{"latlong":{"latitude":"26.9942849","longitude":"75.7513413"},"UID":"E28069950000500EED1791BB","Basicinfo":{"CardNumber":"MPZ171859","MobileNumber":"1111111111"}},{"latlong":{"latitude":"26.9939751","longitude":"75.7512607"},"UID":"E28069950000500EED18F5BA","Basicinfo":{"CardNumber":"MPZ171870","MobileNumber":"1111111111"}},{"latlong":{"latitude":"26.993906","longitude":"75.7512446"},"UID":"E28069950000500EED17CDBB","Basicinfo":{"CardNumber":"MPZ171877","MobileNumber":"7737962292"}},{"latlong":{"latitude":"26.9939688","longitude":"75.7512608"},"UID":"E28069950000400EED12057E","Basicinfo":{"CardNumber":"MPZ171942","MobileNumber":"1111111111"}},{"latlong":{"latitude":"26.9934793","longitude":"75.7511609"},"UID":"E28069950000400EED13CD7D","Basicinfo":{"CardNumber":"MPZ172077","MobileNumber":"1111111111"}},{"latlong":{"latitude":"26.9943659","longitude":"75.7514199"},"UID":"E280117000000217B0C6B5E0","Basicinfo":{"CardNumber":"MPZ179613","MobileNumber":"1111111111"}}],"lineLength":296},"49":{"points":[[26.993119,75.749759],[26.993131,75.749706],[26.992492,75.74955],[26.992581,75.749094]],"Houses":[],"lineLength":124},"50":{"points":[[26.992581,75.749094],[26.992586,75.749052],[26.993219,75.749253],[26.993305,75.748928]],"Houses":[],"lineLength":110},"51":{"points":[[26.993305,75.748928],[26.993307,75.748893],[26.992643,75.748724],[26.992727,75.748413]],"Houses":[],"lineLength":111},"52":{"points":[[26.992727,75.748413],[26.992739,75.748389],[26.993365,75.748567],[26.993307,75.74883]],"Houses":[],"lineLength":101},"53":{"points":[[26.993307,75.74883],[26.993325,75.74883],[26.993445,75.748233],[26.992834,75.748037]],"Houses":[],"lineLength":133},"54":{"points":[[26.992834,75.748037],[26.992812,75.748027],[26.992902,75.74766],[26.993515,75.747836]],"Houses":[],"lineLength":110},"55":{"points":[[26.993515,75.747836],[26.993549,75.747834],[26.993611,75.747501],[26.992992,75.747297]],"Houses":[],"lineLength":109},"56":{"points":[[26.992992,75.747297],[26.992918,75.747435],[26.992629,75.748707],[26.992474,75.749501]],"Houses":[],"lineLength":226},"57":{"points":[[26.992474,75.749501],[26.992464,75.749545],[26.992507,75.749586],[26.992593,75.749612],[26.993106,75.749728],[26.99288,75.750988]],"Houses":[],"lineLength":206},"58":{"points":[[26.99288,75.750988],[26.992781,75.750956],[26.992522,75.750939],[26.99255,75.750645],[26.991973,75.750529]],"Houses":[],"lineLength":134},"59":{"points":[[26.991973,75.750529],[26.991973,75.75051],[26.992553,75.750624],[26.992592,75.750313],[26.991862,75.750172]],"Houses":[],"lineLength":180},"60":{"points":[[26.991862,75.750172],[26.991867,75.750158],[26.992598,75.750288],[26.992634,75.750086]],"Houses":[],"lineLength":103},"61":{"points":[[26.992634,75.750086],[26.992636,75.750029],[26.992625,75.749991],[26.992583,75.749964],[26.992123,75.749874],[26.991923,75.749842]],"Houses":[],"lineLength":89},"62":{"points":[[26.991923,75.749842],[26.99192,75.749825],[26.992087,75.749836],[26.99215,75.749574],[26.992148,75.749541],[26.99183,75.749468]],"Houses":[],"lineLength":86},"63":{"points":[[26.99183,75.749468],[26.991808,75.749456],[26.991886,75.749106],[26.992242,75.749196]],"Houses":[],"lineLength":78},"64":{"points":[[26.992242,75.749196],[26.992241,75.749183],[26.991887,75.749094],[26.991966,75.748785],[26.991966,75.748767],[26.992293,75.748848]],"Houses":[],"lineLength":112},"65":{"points":[[26.992293,75.748848],[26.992282,75.74883],[26.99197,75.748754],[26.992047,75.748408],[26.992424,75.748504]],"Houses":[],"lineLength":115},"66":{"points":[[26.992424,75.748504],[26.992415,75.748487],[26.992035,75.748389],[26.992114,75.748047],[26.992222,75.748055],[26.992544,75.748132]],"Houses":[],"lineLength":128},"67":{"points":[[26.992544,75.748132],[26.992528,75.748113],[26.992036,75.747991],[26.991605,75.747886]],"Houses":[],"lineLength":107},"68":{"points":[[26.991605,75.747886],[26.991599,75.747905],[26.992099,75.748023],[26.992025,75.748373],[26.99153,75.748248]],"Houses":[],"lineLength":150},"69":{"points":[[26.99153,75.748248],[26.991528,75.748266],[26.992021,75.748387],[26.991948,75.748726],[26.991412,75.748576],[26.991225,75.748528]],"Houses":[],"lineLength":174},"70":{"points":[[26.991225,75.748528],[26.991226,75.748547],[26.99194,75.74874],[26.991862,75.749085],[26.990442,75.748675]],"Houses":[],"lineLength":281},"71":{"points":[[26.990442,75.748675],[26.990384,75.748655],[26.990282,75.749018],[26.991238,75.749304]],"Houses":[],"lineLength":154},"72":{"points":[[26.991238,75.749304],[26.991754,75.749439]],"Houses":[],"lineLength":58},"73":{"points":[[26.991754,75.749439],[26.991717,75.749463],[26.990274,75.749056],[26.99019,75.749386]],"Houses":[],"lineLength":203},"74":{"points":[[26.99019,75.749386],[26.990182,75.749434],[26.991148,75.749554],[26.991265,75.749554],[26.991315,75.749573],[26.991336,75.749667],[26.991229,75.750134]],"Houses":[],"lineLength":188},"75":{"points":[[26.991229,75.750134],[26.991134,75.750491],[26.991471,75.750628]],"Houses":[],"lineLength":76},"76":{"points":[[26.991471,75.750628],[26.991504,75.750639],[26.991753,75.749698],[26.991397,75.749596]],"Houses":[],"lineLength":141},"77":{"points":[[26.991397,75.749596],[26.991413,75.749577],[26.991764,75.749684],[26.991516,75.750649],[26.991755,75.75082],[26.991906,75.750894],[26.992448,75.750936],[26.992455,75.750938]],"Houses":[],"lineLength":253},"78":{"points":[[26.992455,75.750938],[26.992434,75.750962],[26.991896,75.750924],[26.991643,75.750777],[26.991504,75.750667],[26.990689,75.750406]],"Houses":[],"lineLength":207},"79":{"points":[[26.990689,75.750406],[26.989371,75.750013]],"Houses":[],"lineLength":151},"80":{"points":[[26.989371,75.750013],[26.989385,75.749984],[26.9903,75.750263],[26.990383,75.749926],[26.991064,75.750106],[26.991168,75.750141]],"Houses":[],"lineLength":232},"81":{"points":[[26.991168,75.750141],[26.991144,75.750116],[26.990189,75.749832],[26.989371,75.749584]],"Houses":[],"lineLength":207},"82":{"points":[[26.989371,75.749584],[26.989336,75.749523],[26.989412,75.749255],[26.989561,75.749233],[26.990125,75.749421]],"Houses":[],"lineLength":116},"83":{"points":[[26.990125,75.749421],[26.990108,75.749389],[26.989558,75.749209],[26.989706,75.748772]],"Houses":[],"lineLength":113},"84":{"points":[[26.989706,75.748772],[26.989828,75.74827],[26.990351,75.748447]],"Houses":[],"lineLength":112},"85":{"points":[[26.990351,75.748447],[26.990396,75.74846],[26.99027,75.748929],[26.989739,75.74876]],"Houses":[],"lineLength":114},"86":{"points":[[26.989739,75.74876],[26.9897,75.748746],[26.989967,75.747625]],"Houses":[],"lineLength":119},"87":{"points":[[26.989967,75.747625],[26.989996,75.747632],[26.989948,75.74782],[26.99019,75.747916],[26.99029,75.747924],[26.990357,75.747868],[26.990512,75.747927],[26.990402,75.748393]],"Houses":[],"lineLength":137},"88":{"points":[[26.990402,75.748393],[26.990431,75.748401],[26.990459,75.748318],[26.991124,75.748527]],"Houses":[],"lineLength":88},"89":{"points":[[26.991124,75.748527],[26.991117,75.748508],[26.990464,75.748291],[26.990546,75.747906],[26.990661,75.747942],[26.991064,75.74805]],"Houses":[],"lineLength":175},"90":{"points":[[26.991064,75.74805],[26.991063,75.748038],[26.990518,75.747882],[26.99036,75.747826],[26.990448,75.747584]],"Houses":[],"lineLength":107},"91":{"points":[[26.990448,75.747584],[26.990457,75.747547],[26.989344,75.747093],[26.988937,75.746945]],"Houses":[],"lineLength":182},"92":{"points":[[26.988937,75.746945],[26.98887,75.74692],[26.989089,75.746247],[26.989409,75.746376]],"Houses":[],"lineLength":116},"93":{"points":[[26.989409,75.746376],[26.989412,75.74636],[26.989093,75.746231],[26.98922,75.745904],[26.989514,75.746034]],"Houses":[],"lineLength":109},"94":{"points":[[26.989514,75.746034],[26.98951,75.746008],[26.989227,75.745894],[26.989335,75.745547],[26.989631,75.745674]],"Houses":[],"lineLength":107},"95":{"points":[[26.989631,75.745674],[26.98962,75.745642],[26.98934,75.745522],[26.989448,75.745213],[26.989878,75.745422]],"Houses":[],"lineLength":121},"96":{"points":[[26.989878,75.745422],[26.989866,75.745388],[26.98945,75.745186],[26.98945,75.745127],[26.98946,75.745066],[26.98957,75.744792],[26.989579,75.744773],[26.989858,75.744891]],"Houses":[],"lineLength":130},"97":{"points":[[26.989858,75.744891],[26.989849,75.744867],[26.98958,75.744748],[26.989726,75.744318],[26.989941,75.744424]],"Houses":[],"lineLength":106},"98":{"points":[[26.989941,75.744424],[26.989938,75.744404],[26.989728,75.744304],[26.989829,75.743995]],"Houses":[],"lineLength":59},"99":{"points":[[26.989829,75.743995],[26.989839,75.743972],[26.990329,75.744165]],"Houses":[],"lineLength":60},"100":{"points":[[26.990329,75.744165],[26.990293,75.744286],[26.990904,75.744559]],"Houses":[],"lineLength":85},"101":{"points":[[26.990904,75.744559],[26.99089,75.744594],[26.990297,75.74432],[26.990187,75.744704]],"Houses":[],"lineLength":114},"102":{"points":[[26.990187,75.744704],[26.990071,75.745055],[26.990733,75.745337]],"Houses":[],"lineLength":115},"103":{"points":[[26.990733,75.745337],[26.990722,75.745356],[26.990055,75.74508],[26.989959,75.745407]],"Houses":[],"lineLength":115},"104":{"points":[[26.989959,75.745407],[26.990626,75.745675]],"Houses":[],"lineLength":78},"105":{"points":[[26.990626,75.745675],[26.990604,75.745691],[26.989952,75.745419],[26.989871,75.745676]],"Houses":[],"lineLength":107},"106":{"points":[[26.989871,75.745676],[26.989859,75.745714],[26.99054,75.746013]],"Houses":[],"lineLength":85},"107":{"points":[[26.99054,75.746013],[26.990527,75.746029],[26.989848,75.745736],[26.989739,75.746057],[26.990496,75.746384]],"Houses":[],"lineLength":206},"108":{"points":[[26.990496,75.746384],[26.990479,75.746392],[26.989733,75.74607],[26.989637,75.746384],[26.990398,75.746694]],"Houses":[],"lineLength":213},"109":{"points":[[26.990398,75.746694],[26.990387,75.746703],[26.989626,75.746395],[26.989531,75.746701]],"Houses":[],"lineLength":123},"110":{"points":[[26.989531,75.746701],[26.989521,75.746737],[26.990548,75.747156],[26.990477,75.74741]],"Houses":[],"lineLength":151},"111":{"points":[[26.990477,75.74741],[26.991457,75.747792]],"Houses":[],"lineLength":115},"112":{"points":[[26.991457,75.747792],[26.991435,75.747763],[26.990508,75.747393],[26.990613,75.747079],[26.991127,75.74728]],"Houses":[],"lineLength":206},"113":{"points":[[26.991127,75.74728],[26.991108,75.747261],[26.990612,75.74706],[26.990736,75.746748],[26.991262,75.746966]],"Houses":[],"lineLength":157},"114":{"points":[[26.991262,75.746966],[26.991233,75.746939],[26.990716,75.746714],[26.990832,75.746419],[26.991362,75.746648]],"Houses":[],"lineLength":160},"115":{"points":[[26.991362,75.746648],[26.991371,75.746632],[26.990845,75.746396],[26.991072,75.745712],[26.991466,75.74588]],"Houses":[],"lineLength":183},"116":{"points":[[26.991466,75.74588],[26.99144,75.745838],[26.99107,75.74569],[26.991209,75.745221],[26.991182,75.745162],[26.990248,75.744773]],"Houses":[],"lineLength":214},"117":{"points":[[26.990248,75.744773],[26.990158,75.744734],[26.990337,75.744123],[26.989773,75.743913],[26.989111,75.74368],[26.989061,75.7439]],"Houses":[],"lineLength":239},"118":{"points":[[26.989061,75.7439],[26.989063,75.743916],[26.989304,75.74399],[26.989302,75.74415],[26.98965,75.744285]],"Houses":[],"lineLength":86},"119":{"points":[[26.98965,75.744285],[26.989681,75.744299],[26.989551,75.74471],[26.989293,75.744594],[26.989286,75.74461]],"Houses":[],"lineLength":79},"120":{"points":[[26.989286,75.74461],[26.989553,75.744733],[26.989436,75.745084],[26.989004,75.74491]],"Houses":[],"lineLength":120},"121":{"points":[[26.989004,75.74491],[26.989016,75.744937],[26.989429,75.745103],[26.989302,75.745488],[26.988885,75.745311]],"Houses":[],"lineLength":141},"122":{"points":[[26.988885,75.745311],[26.988882,75.745324],[26.989311,75.745507],[26.988987,75.746501]],"Houses":[],"lineLength":157},"123":{"points":[[26.988987,75.746501],[26.988852,75.746895],[26.988394,75.746703]],"Houses":[],"lineLength":96},"124":{"points":[[26.988394,75.746703],[26.988375,75.746679],[26.988464,75.746368],[26.988848,75.746507]],"Houses":[],"lineLength":80},"125":{"points":[[26.988848,75.746507],[26.988838,75.746491],[26.988471,75.746357],[26.988574,75.745977],[26.988888,75.746099]],"Houses":[],"lineLength":120},"126":{"points":[[26.988888,75.746099],[26.988876,75.746083],[26.988571,75.745964],[26.988669,75.745646],[26.988908,75.745733]],"Houses":[],"lineLength":99},"127":{"points":[[26.988908,75.745733],[26.988895,75.745713],[26.988643,75.745622],[26.98836,75.74664]],"Houses":[],"lineLength":137},"128":{"points":[[26.988361,75.746629],[26.98834,75.74665],[26.988313,75.746648],[26.98829,75.746625],[26.988256,75.746591],[26.988231,75.746558],[26.988702,75.744751]],"Houses":[],"lineLength":206},"129":{"points":[[26.988702,75.744751],[26.988772,75.744443],[26.988953,75.743672]],"Houses":[],"lineLength":110},"130":{"points":[[26.988953,75.743672],[26.988981,75.743502],[26.988288,75.743199],[26.988486,75.742316]],"Houses":[],"lineLength":189},"131":{"points":[[26.988486,75.742316],[26.988606,75.741791],[26.989906,75.74236],[26.989937,75.742211]],"Houses":[],"lineLength":223},"132":{"points":[[26.989937,75.742211],[26.989946,75.742168],[26.99043,75.742292]],"Houses":[],"lineLength":59},"133":{"points":[[26.99043,75.742292],[26.990457,75.7423],[26.990514,75.741971],[26.989781,75.741737]],"Houses":[],"lineLength":120},"134":{"points":[[26.989781,75.741737],[26.989787,75.741722],[26.990526,75.741956],[26.990572,75.741593],[26.990063,75.741456]],"Houses":[],"lineLength":181},"135":{"points":[[26.990063,75.741456],[26.990068,75.741434],[26.990581,75.741583],[26.990652,75.741281]],"Houses":[],"lineLength":91},"136":{"points":[[26.990652,75.741281],[26.990654,75.741265],[26.990018,75.741081]],"Houses":[],"lineLength":74},"137":{"points":[[26.990018,75.741081],[26.990021,75.741073],[26.990662,75.741252],[26.990734,75.740963]],"Houses":[],"lineLength":103},"138":{"points":[[26.990734,75.740963],[26.990742,75.740944],[26.990554,75.740874],[26.990526,75.740851],[26.990346,75.740801]],"Houses":[],"lineLength":48},"139":{"points":[[26.990346,75.740801],[26.990351,75.740781],[26.990533,75.74084],[26.990564,75.740868],[26.990743,75.74093],[26.990805,75.740676],[26.990787,75.740636],[26.990731,75.740596],[26.990417,75.740526]],"Houses":[],"lineLength":121},"140":{"points":[[26.990417,75.740526],[26.990418,75.740516],[26.990728,75.740585],[26.990771,75.740605],[26.990809,75.740644],[26.990856,75.740633],[26.990999,75.740617],[26.991513,75.740684]],"Houses":[],"lineLength":125},"141":{"points":[[26.991513,75.740684],[26.99154,75.74069],[26.99143,75.741192],[26.990849,75.741014]],"Houses":[],"lineLength":121},"142":{"points":[[26.990849,75.741014],[26.990842,75.741026],[26.991414,75.7412],[26.991312,75.741572],[26.990949,75.74145]],"Houses":[],"lineLength":147},"143":{"points":[[26.990949,75.74145],[26.990952,75.74147],[26.991329,75.741594],[26.99124,75.741943],[26.990705,75.741773]],"Houses":[],"lineLength":143},"144":{"points":[[26.990705,75.741773],[26.990678,75.741772],[26.990595,75.741753],[26.99053,75.74212],[26.990852,75.74221]],"Houses":[],"lineLength":86},"145":{"points":[[26.990852,75.74221],[26.990839,75.742217],[26.99051,75.742127],[26.990586,75.741768],[26.990726,75.7418],[26.991205,75.741947]],"Houses":[],"lineLength":146},"146":{"points":[[26.991205,75.741947],[26.99124,75.741958],[26.991199,75.74221],[26.991194,75.742245],[26.993346,75.742361]],"Houses":[],"lineLength":271},"147":{"points":[[26.993346,75.742361],[26.993344,75.742337],[26.993253,75.742329],[26.99328,75.741999],[26.992441,75.741956]],"Houses":[],"lineLength":138},"148":{"points":[[26.992441,75.741956],[26.991318,75.741896]],"Houses":[],"lineLength":124},"149":{"points":[[26.991309,75.741895],[26.991282,75.741892],[26.991376,75.741526],[26.992388,75.741574]],"Houses":[],"lineLength":154},"150":{"points":[[26.992388,75.741574],[26.992402,75.741199],[26.991508,75.741156]],"Houses":[],"lineLength":136},"151":{"points":[[26.991508,75.741156],[26.991465,75.741164],[26.991577,75.740702],[26.992407,75.740783]],"Houses":[],"lineLength":144},"152":{"points":[[26.992407,75.740783],[26.992442,75.740789],[26.992418,75.74157],[26.99325,75.741599]],"Houses":[],"lineLength":173},"153":{"points":[[26.99325,75.741599],[26.993381,75.74161],[26.99341,75.74154],[26.993422,75.741237],[26.992473,75.741194]],"Houses":[],"lineLength":157},"154":{"points":[[26.992473,75.741194],[26.992446,75.741199],[26.992461,75.740798],[26.993404,75.740908]],"Houses":[],"lineLength":147},"155":{"points":[[26.993404,75.740908],[26.993799,75.74099],[26.993708,75.741624],[26.993597,75.742426]],"Houses":[],"lineLength":188},"156":{"points":[[26.993597,75.742426],[26.993614,75.742427],[26.993813,75.740985],[26.994067,75.741036]],"Houses":[],"lineLength":175},"157":{"points":[[26.994067,75.741036],[26.994106,75.741046],[26.9939,75.742357]],"Houses":[],"lineLength":136},"158":{"points":[[26.9939,75.742357],[26.993913,75.742357],[26.994127,75.74105],[26.994579,75.741144]],"Houses":[],"lineLength":184},"159":{"points":[[26.994579,75.741144],[26.994632,75.741156],[26.994534,75.741821],[26.994496,75.742084]],"Houses":[],"lineLength":99},"160":{"points":[[26.994496,75.742084],[26.99452,75.742087],[26.994556,75.741838],[26.995015,75.741948],[26.994981,75.742181]],"Houses":[],"lineLength":103},"161":{"points":[[26.994981,75.742181],[26.995011,75.742197],[26.995092,75.741564],[26.994636,75.741472]],"Houses":[],"lineLength":118},"162":{"points":[[26.994636,75.741472],[26.994614,75.741462],[26.994664,75.741116],[26.995088,75.741183]],"Houses":[],"lineLength":84},"163":{"points":[[26.995088,75.741183],[26.9950835,75.7411468],[26.994639,75.7410824],[26.9946366,75.741128],[26.9941299,75.7410314]],"Houses":[],"lineLength":114},"164":{"points":[[26.9941299,75.7410314],[26.9940961,75.7410189],[26.9942431,75.7401673],[26.9938643,75.7400989]],"Houses":[],"lineLength":132},"165":{"points":[[26.9938643,75.7400989],[26.9938329,75.7400882],[26.9937075,75.7409237]],"Houses":[],"lineLength":87},"166":{"points":[[26.9937075,75.7409237],[26.9937027,75.7409412],[26.9936895,75.7409304],[26.9938138,75.7400145],[26.9933448,75.7399387]],"Houses":[],"lineLength":148},"167":{"points":[[26.9933448,75.7399387],[26.9920156,75.7398395]],"Houses":[],"lineLength":147},"168":{"points":[[26.9920156,75.7398395],[26.9919823,75.7398368],[26.9919542,75.7402049],[26.9928761,75.7402829],[26.9928737,75.7403285]],"Houses":[],"lineLength":147},"169":{"points":[[26.9928737,75.7403285],[26.9919518,75.7402292],[26.9919171,75.7406785]],"Houses":[],"lineLength":147},"170":{"points":[[26.9919171,75.7406785],[26.9919057,75.7406758],[26.9919415,75.7402252],[26.991742,75.7402]],"Houses":[],"lineLength":68},"171":{"points":[[26.991742,75.7402],[26.9917411,75.7401897],[26.9919418,75.7402151],[26.9919634,75.7398611]],"Houses":[],"lineLength":58},"172":{"points":[[26.9919634,75.7398611],[26.9919633,75.7398303],[26.9910228,75.739719]],"Houses":[],"lineLength":107},"173":{"points":[[26.9910228,75.739719],[26.9909121,75.7397083],[26.9907448,75.7398036],[26.9907986,75.7398921],[26.9908213,75.7399779]],"Houses":[],"lineLength":52},"174":{"points":[[26.9908213,75.7399779],[26.9908243,75.7399943],[26.991484,75.7400721]],"Houses":[],"lineLength":75},"175":{"points":[[26.991484,75.7400721],[26.991484,75.7400949],[26.9908196,75.7400265],[26.9907777,75.7402639]],"Houses":[],"lineLength":100},"176":{"points":[[26.9907777,75.7402639],[26.9907706,75.7402827],[26.9915497,75.7403578]],"Houses":[],"lineLength":88},"177":{"points":[[26.9915497,75.7403578],[26.9915461,75.7403752],[26.9907514,75.7402961],[26.9906929,75.7405294]],"Houses":[],"lineLength":114},"178":{"points":[[26.9906929,75.7405294],[26.9906872,75.74053],[26.9907457,75.7402853],[26.9907762,75.7401572],[26.9907965,75.7399848],[26.9907386,75.7398635],[26.9907147,75.7398226],[26.9905462,75.7399072]],"Houses":[],"lineLength":95},"179":{"points":[[26.9905462,75.7399072],[26.9905367,75.7399092],[26.9905385,75.7399615],[26.990433,75.740432]],"Houses":[],"lineLength":54},"180":{"points":[[26.990433,75.740432],[26.9904214,75.7404285],[26.9905086,75.7400262],[26.9905158,75.7399122],[26.990113,75.739766]],"Houses":[],"lineLength":100},"181":{"points":[[26.990113,75.739766],[26.990089,75.7397547],[26.9904989,75.7394543]],"Houses":[],"lineLength":57},"182":{"points":[[26.9904989,75.7394543],[26.9905194,75.7394147],[26.9913595,75.7387871]],"Houses":[],"lineLength":116},"183":{"points":[[26.9913595,75.7387871],[26.991364,75.738803],[26.9909911,75.7390833],[26.9905274,75.7394347],[26.9906971,75.7397418]],"Houses":[],"lineLength":149},"184":{"points":[[26.9906971,75.7397418],[26.9907202,75.739789],[26.9914444,75.7393001]],"Houses":[],"lineLength":99},"185":{"points":[[26.9914444,75.7393001],[26.9914631,75.7392838],[26.9920008,75.7393777],[26.991959,75.7397559]],"Houses":[],"lineLength":100},"186":{"points":[[26.991959,75.7397559],[26.9919661,75.7397577],[26.9920103,75.7393668],[26.9929687,75.739454]],"Houses":[],"lineLength":146},"187":{"points":[[26.9929687,75.739454],[26.9935863,75.7395265],[26.9938707,75.7395801],[26.9938743,75.7395573]],"Houses":[],"lineLength":103},"188":{"points":[[26.9938743,75.7395573],[26.9933204,75.7394774],[26.9928197,75.7394251]],"Houses":[],"lineLength":117},"189":{"points":[[26.9928197,75.7394251],[26.9923124,75.7393757],[26.9920244,75.7393462],[26.9920531,75.7390109]],"Houses":[],"lineLength":121},"190":{"points":[[26.9920531,75.7390109],[26.9920586,75.7389431],[26.9921213,75.7389448],[26.9921404,75.7386604]],"Houses":[],"lineLength":42},"191":{"points":[[26.9921404,75.7386604],[26.9921526,75.7386629],[26.992135,75.738943],[26.9926318,75.7389754]],"Houses":[],"lineLength":84},"192":{"points":[[26.9926318,75.7389754],[26.9928573,75.7389926],[26.9928955,75.7385031]],"Houses":[],"lineLength":73},"193":{"points":[[26.9928955,75.7385031],[26.9929084,75.7385018],[26.9928665,75.738998],[26.9928665,75.7390101],[26.9937042,75.7391228]],"Houses":[],"lineLength":145},"194":{"points":[[26.9937042,75.7391228],[26.9937072,75.7391093],[26.9934335,75.739061],[26.9934658,75.7387338],[26.9938099,75.7387606]],"Houses":[],"lineLength":102},"195":{"points":[[26.9938099,75.7387606],[26.9938087,75.7387391],[26.9931491,75.7386868]],"Houses":[],"lineLength":75},"196":{"points":[[26.9931491,75.7386868],[26.9931443,75.7386775],[26.9934478,75.7386962],[26.9934717,75.7383717],[26.994013,75.738416]],"Houses":[],"lineLength":127},"197":{"points":[[26.994013,75.738416],[26.9940119,75.7384039],[26.9934502,75.7383489],[26.9931789,75.7382885],[26.9930057,75.7380015]],"Houses":[],"lineLength":128},"198":{"points":[[26.9930057,75.7380015],[26.9930104,75.7379942],[26.9931795,75.7382745],[26.9932136,75.7382892],[26.9934138,75.7383261],[26.9934783,75.7383326],[26.9934855,75.7381556]],"Houses":[],"lineLength":85},"199":{"points":[[26.9934855,75.7381556],[26.993483,75.73811],[26.9932327,75.7376857],[26.9929734,75.737854]],"Houses":[],"lineLength":88},"200":{"points":[[26.9929734,75.737854],[26.9926374,75.7380888],[26.9927856,75.7383637]],"Houses":[],"lineLength":75},"201":{"points":[[26.9927856,75.7383637],[26.9927783,75.7383752],[26.9926242,75.7380962],[26.9921999,75.7383913]],"Houses":[],"lineLength":89},"202":{"points":[[26.9921999,75.7383913],[26.9918606,75.7386294],[26.9917709,75.7388708]],"Houses":[],"lineLength":70},"203":{"points":[[26.9917709,75.7388708],[26.9917554,75.7388721],[26.9918438,75.7386173],[26.9922716,75.7383155],[26.9926552,75.7380513]],"Houses":[],"lineLength":134},"204":{"points":[[26.9926552,75.7380513],[26.9932226,75.7376653],[26.9930685,75.7373756]],"Houses":[],"lineLength":107},"205":{"points":[[26.9930685,75.7373756],[26.9930469,75.7373327],[26.9921077,75.7379282]],"Houses":[],"lineLength":124},"206":{"points":[[26.9921077,75.7379282],[26.9911258,75.738645]],"Houses":[],"lineLength":129},"207":{"points":[[26.9911258,75.738645],[26.989997,75.7394343]],"Houses":[],"lineLength":147},"totalLines":207,"totalWardLength":26384,"totalHouseCount":245}